biszx_odoo_mcp/__init__.py
biszx_odoo_mcp/__main__.py
biszx_odoo_mcp/exceptions.py
biszx_odoo_mcp/main.py
biszx_odoo_mcp/server/__init__.py
biszx_odoo_mcp/server/context.py
biszx_odoo_mcp/server/resources.py
biszx_odoo_mcp/server/response.py
biszx_odoo_mcp/server/tools.py
biszx_odoo_mcp/tools/__init__.py
biszx_odoo_mcp/tools/config.py
biszx_odoo_mcp/tools/odoo_client.py
biszx_odoo_mcp-1.2.0.dist-info/licenses/LICENSE
biszx_odoo_mcp-1.2.0.dist-info/METADATA
biszx_odoo_mcp-1.2.0.dist-info/WHEEL
biszx_odoo_mcp-1.2.0.dist-info/entry_points.txt
biszx_odoo_mcp-1.2.0.dist-info/top_level.txt
biszx_odoo_mcp-1.2.0.dist-info/RECORD
