Metadata-Version: 2.4
Name: biszx-odoo-mcp
Version: 1.2.0
Summary: MCP Server for Odoo Integration
Author-email: Biszx <isares.br@gmail.com>
License: MIT
Project-URL: Homepage, https://gitlab.com/biszx/biszx-odoo-mcp
Project-URL: Issues, https://gitlab.com/biszx/biszx-odoo-mcp/issues
Keywords: odoo,mcp,server
Classifier: License :: OSI Approved :: MIT License
Classifier: Programming Language :: Python :: 3
Classifier: Programming Language :: Python :: 3.10
Classifier: Operating System :: OS Independent
Requires-Python: >=3.10
License-File: LICENSE
Requires-Dist: asyncio>=3.4.3
Requires-Dist: loguru>=0.7.3
Requires-Dist: mcp[cli]>=1.9.4
Requires-Dist: odoorpc>=0.10.1
Dynamic: license-file
